genomeview/__init__.py
genomeview/axis.py
genomeview/bamtrack.py
genomeview/bedtrack.py
genomeview/convenience.py
genomeview/export.py
genomeview/genomesource.py
genomeview/genomeview.py
genomeview/graphtrack.py
genomeview/intervaltrack.py
genomeview/quickconsensus.py
genomeview/svg.py
genomeview/track.py
genomeview/utilities.py
genomeview-1.1.4.dist-info/LICENSE
genomeview-1.1.4.dist-info/METADATA
genomeview-1.1.4.dist-info/WHEEL
genomeview-1.1.4.dist-info/top_level.txt
genomeview-1.1.4.dist-info/RECORD
